pyjls/__init__.py
pyjls/__main__.py
pyjls/binding.cpython-313-aarch64-linux-gnu.so
pyjls/structs.py
pyjls/time64.py
pyjls/version.py
pyjls/entry_points/__init__.py
pyjls/entry_points/annotate.py
pyjls/entry_points/copy.py
pyjls/entry_points/csv.py
pyjls/entry_points/export.py
pyjls/entry_points/extract.py
pyjls/entry_points/info.py
pyjls/entry_points/plot.py
pyjls/entry_points/timestamp_patch.py
pyjls/test/__init__.py
pyjls/test/test_binding.py
pyjls/test/test_time64.py
pyjls/v1/__init__.py
pyjls-0.15.0.dist-info/METADATA
pyjls-0.15.0.dist-info/WHEEL
pyjls-0.15.0.dist-info/entry_points.txt
pyjls-0.15.0.dist-info/top_level.txt
pyjls-0.15.0.dist-info/RECORD
pyjls-0.15.0.dist-info/licenses/LICENSE
