Metadata-Version: 2.4
Name: pyjls
Version: 0.15.0
Summary: Joulescope™ file format
Home-page: https://joulescope.readthedocs.io
Author: Jetperch LLC
Author-email: joulescope-dev@jetperch.com
License: Apache 2.0
Project-URL: Bug Reports, https://github.com/jetperch/jls/issues
Project-URL: Funding, https://www.joulescope.com
Project-URL: Twitter, https://twitter.com/joulescope
Project-URL: Source, https://github.com/jetperch/jls/
Keywords: JLS,Joulescope
Classifier: Development Status :: 5 - Production/Stable
Classifier: Intended Audience :: Developers
Classifier: Intended Audience :: End Users/Desktop
Classifier: Intended Audience :: Science/Research
Classifier: License :: OSI Approved :: Apache Software License
Classifier: Operating System :: Microsoft :: Windows :: Windows 11
Classifier: Operating System :: MacOS :: MacOS X
Classifier: Operating System :: POSIX :: Linux
Classifier: Programming Language :: Python
Classifier: Programming Language :: Python :: 3
Classifier: Programming Language :: Python :: 3.10
Classifier: Programming Language :: Python :: 3.11
Classifier: Programming Language :: Python :: 3.12
Classifier: Programming Language :: Python :: 3.13
Classifier: Programming Language :: Python :: Implementation :: CPython
Classifier: Topic :: Scientific/Engineering
Classifier: Topic :: Software Development :: Embedded Systems
Classifier: Topic :: Software Development :: Testing
Classifier: Topic :: System :: Hardware :: Hardware Drivers
Classifier: Topic :: Utilities
Requires-Python: ~=3.10
License-File: LICENSE
Requires-Dist: numpy<3,>=2.1.0
Requires-Dist: pywin32; platform_system == "Windows"
Dynamic: author
Dynamic: author-email
Dynamic: classifier
Dynamic: description
Dynamic: description-content-type
Dynamic: home-page
Dynamic: keywords
Dynamic: license
Dynamic: license-file
Dynamic: project-url
Dynamic: requires-dist
Dynamic: requires-python
Dynamic: summary
